<?xml version="1.0" encoding="UTF-8"?>
<!-- edited with XMLSpy v2010 (http://www.altova.com) by Rich Andrews (self) -->
<utilitybill id="2247634543" xmlns:xsi="http://www.w3.org/2001/XMLSchema-instance" xsi:noNamespaceSchemaLocation="..\UtilityBill.xsd">
	<car>
		<accountnumber>94443-01819</accountnumber>
		<serviceaddress>
			<addressee>T C Commons</addressee>
			<street>1103 West Chester PI, ST 12-A</street>
			<city>West Chester</city>
			<state>PA</state>
			<country>USA</country>
			<postalcode/>
			<telephonenumber>610-688-8985</telephonenumber>
			<hours/>
		</serviceaddress>
		<billingaddress>
			<addressee>T C Commons</addressee>
			<street>C/O Family Laundry Mat</street>
			<city>West Chester</city>
			<state>PA</state>
			<country>USA</country>
			<postalcode>19382-5004</postalcode>
			<telephonenumber/>
			<hours/>
		</billingaddress>
	</car>
	<uar>
		<tin/>
		<customerservice>
			<addressee>Business Account Services PECO</addressee>
			<street>2301 Market St.</street>
			<city>Philadelphia</city>
			<state>PA</state>
			<country>USA</country>
			<postalcode>19101</postalcode>
			<telephonenumber>800-980-9655</telephonenumber>
			<hours/>
		</customerservice>
		<paymentlocation>
			<addressee>PECO Energy - Payment Processing</addressee>
			<street>PO Box 37629</street>
			<city>Philadelphia</city>
			<state>PA</state>
			<country>USA</country>
			<postalcode>19101</postalcode>
			<telephonenumber/>
			<hours/>
		</paymentlocation>
		<paymentlocation>
			<addressee>PECO Energy</addressee>
			<street>2301 Market St.</street>
			<city>Philadelphia</city>
			<state>PA</state>
			<country>USA</country>
			<postalcode>19101</postalcode>
			<telephonenumber>1-877-432-9384</telephonenumber>
			<hours>M-F 8:30-5PM</hours>
		</paymentlocation>
		<emergencycontact>
			<addressee>Emergency and Repairs</addressee>
			<street/>
			<city/>
			<state/>
			<country/>
			<postalcode/>
			<telephonenumber>1-800-841-4141</telephonenumber>
			<hours/>
		</emergencycontact>
	</uar>
	<unknownaddress description="Business Inquiry">
		<addressee/>
		<street/>
		<city/>
		<state/>
		<country/>
		<postalcode/>
		<telephonenumber>1-800-980-9655</telephonenumber>
		<hours/>
	</unknownaddress>
	<summary>
		<priorbalance>0.0</priorbalance>
		<previouspayment>
			<payee>PECO</payee>
			<amount>2501.91</amount>
		</previouspayment>
		<billperiodbegin>2009-09-03</billperiodbegin>
		<billperiodend>2009-10-05</billperiodend>
		<issuedate>2009-10-06</issuedate>
		<currentcharges service="gas">1610.53</currentcharges>
		<currentcharges service="electric">955.91</currentcharges>
		<totaldue>2566.44</totaldue>
		<duedate>2009-10-28</duedate>
		<latepayment>
			<penalty/>
			<amount/>
		</latepayment>
	</summary>
	<details service="gas">
		<rateschedule>
			<name>Commercial Service</name>
		</rateschedule>
		<chargegroup type="Generation/Supply">
			<charges>
				<charge>
					<description>Natural Gas Supply Charge</description>
					<quantity units="CCF">1374</quantity>
					<rate units="dollars">0.57779</rate>
					<total>793.88</total>
				</charge>
			</charges>
		</chargegroup>
		<chargegroup type="Distribution">
			<charges>
				<charge>
					<description>Customer Charge</description>
					<total>25.00</total>
				</charge>
				<charge>
					<description>Distribution Charges</description>
					<quantity units="CCF">1374</quantity>
					<rate units="dollars">0.37785</rate>
					<total>519.17</total>
				</charge>
				<charge>
					<description>Balancing Service Charges</description>
					<quantity units="CCF">1374</quantity>
					<rate units="dollars">0.04816</rate>
					<total>66.17</total>
				</charge>
				<charge>
					<description>Gas Cost Adjustment Charge</description>
					<quantity units="CCF">1374</quantity>
					<rate units="dollars">0.08269</rate>
					<total>113.62</total>
				</charge>
			</charges>
		</chargegroup>
		<chargegroup type="Tax">
			<charges>
				<charge>
					<description>Sales Tax Adjustment</description>
					<total>1.52</total>
				</charge>
				<charge>
					<description>Sales Tax</description>
					<total>91.17</total>
				</charge>
			</charges>
		</chargegroup>
		<total>1610.53</total>
	</details>
	<details service="electric">
		<rateschedule>
			<name>Commercial Service</name>
		</rateschedule>
		<chargegroup type="Generation/Supply">
			<charges>
				<charge>
					<description>Generation Charges</description>
					<quantity units="kWh">2120</quantity>
					<rate units="">0.12710</rate>
					<total>269.45</total>
				</charge>
				<charge>
					<description>Generation Charges</description>
					<quantity units="kWh">4080</quantity>
					<rate units="dollars">0.05000</rate>
					<total>204.00</total>
				</charge>
			</charges>
		</chargegroup>
		<chargegroup type="Distribution">
			<charges>
				<charge>
					<description>Customer Charge</description>
					<total>23.94</total>
				</charge>
				<charge>
					<description>Distribution Charge</description>
					<quantity units="kWh">2120</quantity>
					<rate units="dollars">0.03640</rate>
					<total>77.17</total>
				</charge>
				<charge>
					<description>Distribution Charge</description>
					<quantity units="kWh">4080</quantity>
					<rate units="dollars">0.01080</rate>
					<total>44.06</total>
				</charge>
				<charge>
					<description>Transition Charge</description>
					<quantity units="kWh">2120</quantity>
					<rate units="dollars">0.07270</rate>
					<total>154.12</total>
				</charge>
				<charge>
					<description>Transition Charge</description>
					<quantity units="kWh">4080</quantity>
					<rate units="dollars">0.02170</rate>
					<total>88.54</total>
				</charge>
			</charges>
		</chargegroup>
		<chargegroup type="Transmission">
			<charges>
				<charge>
					<description>Transmission Charge</description>
					<quantity units="kWh">2120</quantity>
					<rate units="dollars">0.01290</rate>
					<total>27.35</total>
				</charge>
				<charge>
					<description>Transmission Charge</description>
					<quantity units="kWh">4080</quantity>
					<rate units="dollars">0.00380</rate>
					<total>15.50</total>
				</charge>
			</charges>
		</chargegroup>
		<chargegroup type="Tax">
			<charges>
				<charge>
					<description>State Tax Adjustment</description>
					<total>-2.33</total>
				</charge>
				<charge>
					<description>Sales Tax</description>
					<total>54.11</total>
				</charge>
			</charges>
		</chargegroup>
		<total>955.91</total>
	</details>
	<billableusage service="gas">
		<rateschedule>
			<name>Commercial Service</name>
		</rateschedule>
		<usage>
			<description>Total CCF Used</description>
			<quantity units="CCF">1374</quantity>
		</usage>
	</billableusage>
	<billableusage service="electric">
		<rateschedule>
			<name>Commercial Service</name>
		</rateschedule>
		<usage>
			<description>Total kW Billed</description>
			<quantity units="kW">26.5</quantity>
		</usage>
		<usage>
			<description>Total kWh Used</description>
			<quantity units="kWh">6200</quantity>
		</usage>
	</billableusage>
	<measuredusage service="gas">
		<meter>
			<estimated>false</estimated>
			<identifier>027870434</identifier>
			<register>
				<identifier>027870434</identifier>
				<description>Total CCF</description>
				<units>CCF</units>
				<priorreading>46654</priorreading>
				<presentreading>47485</presentreading>
				<factor>1</factor>
				<total>831</total>
			</register>
		</meter>
		<meter>
			<estimated>false</estimated>
			<identifier>028702956</identifier>
			<register>
				<identifier>028702956</identifier>
				<description>Total CCF</description>
				<units>CCF</units>
				<priorreading>49159</priorreading>
				<presentreading>49702</presentreading>
				<factor>1</factor>
				<total>543</total>
			</register>
		</meter>
		<nextreaddate>2009-11-04</nextreaddate>
	</measuredusage>
	<measuredusage service="electric">
		<meter>
			<estimated>false</estimated>
			<identifier>084010385</identifier>
			<register>
				<identifier>084010385</identifier>
				<description>Total kWh</description>
				<units>kWh</units>
				<priorreading>15421</priorreading>
				<presentreading>15576</presentreading>
				<factor>40</factor>
				<total>6200</total>
			</register>
		</meter>
		<meter>
			<estimated>false</estimated>
			<identifier>084010385</identifier>
			<register>
				<identifier>084010385</identifier>
				<description>Peak kW</description>
				<units>kW</units>
				<priorreading>0.00</priorreading>
				<presentreading>0.66</presentreading>
				<factor>40</factor>
				<total>26.48</total>
			</register>
		</meter>
		<nextreaddate>2009-11-04</nextreaddate>
	</measuredusage>
</utilitybill>
